Metadata-Version: 2.1
Name: sap-rfc-data-collector
Version: 0.7
Summary: Collect data from SAP tables
Home-page: https://github.com/victorouttes/sap-rfc-data-collector
Author: Victor Outtes
Author-email: victor.outtes@gmail.com
License: MIT
Download-URL: https://github.com/victorouttes/sap-rfc-data-collector/archive/refs/tags/0.7.tar.gz
Keywords: sap,data,rfc,read_table,ec3,hana
Platform: UNKNOWN
Classifier: Development Status :: 5 - Production/Stable
Classifier: Intended Audience :: Developers
Classifier: Topic :: Software Development :: Build Tools
Classifier: License :: OSI Approved :: MIT License
Classifier: Programming Language :: Python :: 3
Classifier: Programming Language :: Python :: 3.4
Classifier: Programming Language :: Python :: 3.5
Classifier: Programming Language :: Python :: 3.6
License-File: LICENSE
